pysimgame/__init__.py
pysimgame/game_manager.py
pysimgame/menu.py
pysimgame/model.py
pysimgame/new_game.py
pysimgame/regions_display.py
pysimgame/speed.py
pysimgame/statistics.py
pysimgame/types.py
pysimgame/update_game.py
pysimgame/actions/__init__.py
pysimgame/actions/actions.py
pysimgame/actions/gui.py
pysimgame/events/__init__.py
pysimgame/fonts/__init__.py
pysimgame/links/__init__.py
pysimgame/links/connexions.py
pysimgame/links/exports_methods.py
pysimgame/links/manager.py
pysimgame/links/modifiers.py
pysimgame/links/shared_variables.py
pysimgame/plotting/__init__.py
pysimgame/plotting/manager.py
pysimgame/plotting/plot.py
pysimgame/utils/__init__.py
pysimgame/utils/directories.py
pysimgame/utils/dynamic_menu.py
pysimgame/utils/gui_utils.py
pysimgame/utils/images.py
pysimgame/utils/logging.py
pysimgame/utils/maths.py
pysimgame/utils/pysimgame_settings.py
pysimgame/utils/strings.py
pysimgame-0.1.dist-info/METADATA
pysimgame-0.1.dist-info/WHEEL
pysimgame-0.1.dist-info/top_level.txt
pysimgame-0.1.dist-info/RECORD
