Metadata-Version: 2.1
Name: pysimgame
Version: 0.1
Summary: View, interact and play with simulations using pygame.
Home-page: https://github.com/ScienceGamez/pysimgame
Author: Lionel42
Maintainer: Lionel42
Maintainer-email: lionel@sciencegames.ch
License: WTFPL - Do What the Fuck You Want to Public License
Project-URL: Source Code, https://github.com/ScienceGamez/pysimgame
Platform: UNKNOWN
Classifier: Development Status :: 3 - Alpha
Classifier: Programming Language :: Python :: 3
Classifier: License :: Public Domain
Classifier: Operating System :: OS Independent
Classifier: Topic :: Scientific/Engineering
Classifier: Topic :: Games/Entertainment :: Simulation
Classifier: Topic :: Software Development :: Libraries :: Python Modules
Classifier: Topic :: Software Development :: Libraries :: pygame
Classifier: Typing :: Typed
Requires-Python: >=3.9
Requires-Dist: pygame (>=2.0.0)
Requires-Dist: pysd (>=1.11.0)
Requires-Dist: pygame-gui (>=0.6.0)
Requires-Dist: pygame-matplotlib
